syno_api/__init__.py
syno_api/api.py
syno_api/base.py
syno_api/exceptions.py
syno_api/entities/__init__.py
syno_api/entities/base.py
syno_api/entities/downloadstation.py
syno_api-0.0.1.dist-info/METADATA
syno_api-0.0.1.dist-info/WHEEL
syno_api-0.0.1.dist-info/top_level.txt
syno_api-0.0.1.dist-info/RECORD
